{
  "main": {
    "id": "44e2901ebbfa05b6",
    "type": "split",
    "children": [
      {
        "id": "6e97a62f169c8035",
        "type": "tabs",
        "children": [
          {
            "id": "cafbe99e8ab2affd",
            "type": "leaf",
            "state": {
              "type": "empty",
              "state": {},
              "icon": "lucide-file",
              "title": "Yeni sekme"
            }
          }
        ]
      }
    ],
    "direction": "vertical"
  },
  "left": {
    "id": "481a6efbac6261ac",
    "type": "split",
    "children": [
      {
        "id": "903a743d7de952cb",
        "type": "tabs",
        "children": [
          {
            "id": "ef549c211a15103b",
            "type": "leaf",
            "state": {
              "type": "file-explorer",
              "state": {
                "sortOrder": "alphabetical",
                "autoReveal": false
              },
              "icon": "lucide-folder-closed",
              "title": "Dosya Gezgini"
            }
          },
          {
            "id": "5b88030c12792c27",
            "type": "leaf",
            "state": {
              "type": "search",
              "state": {
                "query": "",
                "matchingCase": false,
                "explainSearch": false,
                "collapseAll": false,
                "extraContext": false,
                "sortOrder": "alphabetical"
              },
              "icon": "lucide-search",
              "title": "Ara"
            }
          },
          {
            "id": "8451c170136c045c",
            "type": "leaf",
            "state": {
              "type": "bookmarks",
              "state": {},
              "icon": "lucide-bookmark",
              "title": "Yer İmleri"
            }
          }
        ]
      }
    ],
    "direction": "horizontal",
    "width": 564.5
  },
  "right": {
    "id": "ed60a9aeb131a731",
    "type": "split",
    "children": [
      {
        "id": "73e07bbb0d13d4ea",
        "type": "tabs",
        "children": [
          {
            "id": "266bb0166a7f3956",
            "type": "leaf",
            "state": {
              "type": "backlink",
              "state": {
                "collapseAll": false,
                "extraContext": false,
                "sortOrder": "alphabetical",
                "showSearch": false,
                "searchQuery": "",
                "backlinkCollapsed": false,
                "unlinkedCollapsed": true
              },
              "icon": "links-coming-in",
              "title": "Geri Bağlantılar"
            }
          },
          {
            "id": "0e0d32502a156e29",
            "type": "leaf",
            "state": {
              "type": "outgoing-link",
              "state": {
                "linksCollapsed": false,
                "unlinkedCollapsed": true
              },
              "icon": "links-going-out",
              "title": "Giden bağlantılar"
            }
          },
          {
            "id": "39d389ffb85b0bc4",
            "type": "leaf",
            "state": {
              "type": "tag",
              "state": {
                "sortOrder": "frequency",
                "useHierarchy": true,
                "showSearch": false,
                "searchQuery": ""
              },
              "icon": "lucide-tags",
              "title": "Etiketler"
            }
          },
          {
            "id": "0225d574d39012f2",
            "type": "leaf",
            "state": {
              "type": "all-properties",
              "state": {
                "sortOrder": "frequency",
                "showSearch": false,
                "searchQuery": ""
              },
              "icon": "lucide-archive",
              "title": "Tüm özellikler"
            }
          },
          {
            "id": "4dd08e43b26a34af",
            "type": "leaf",
            "state": {
              "type": "outline",
              "state": {
                "file": "Başlıksız.canvas",
                "followCursor": false,
                "showSearch": false,
                "searchQuery": ""
              },
              "icon": "lucide-list",
              "title": "Başlıksız ana hatları"
            }
          }
        ]
      }
    ],
    "direction": "horizontal",
    "width": 300,
    "collapsed": true
  },
  "left-ribbon": {
    "hiddenItems": {
      "switcher:Hızlı geçişi aç": false,
      "graph:Grafik görünümünü aç": false,
      "canvas:Yeni tuval oluşturun": false,
      "daily-notes:Bugünün Notunu Aç": false,
      "templates:Şablon ekle": false,
      "command-palette:Komut paletini aç": false,
      "bases:Yeni taban oluştur": false
    }
  },
  "active": "ef549c211a15103b",
  "lastOpenFiles": [
    "Başlıksız.base",
    "Başlıksız.md",
    "Başlıksız",
    "Başlıksız 1.canvas",
    "Hoş geldiniz.md",
    "Başlıksız.canvas"
  ]
}